MANIFEST.in
README.md
setup.py
dash_dangerously_set_inner_html/__init__.py
dash_dangerously_set_inner_html/bundle.js
dash_dangerously_set_inner_html/metadata.json
dash_dangerously_set_inner_html/version.py
dash_dangerously_set_inner_html.egg-info/PKG-INFO
dash_dangerously_set_inner_html.egg-info/SOURCES.txt
dash_dangerously_set_inner_html.egg-info/dependency_links.txt
dash_dangerously_set_inner_html.egg-info/top_level.txt