Metadata-Version: 1.0
Name: dash-dangerously-set-inner-html
Version: 0.0.1
Summary: A dash component for specifying raw HTML
Home-page: UNKNOWN
Author: plotly
Author-email: UNKNOWN
License: MIT
Platform: UNKNOWN
